wagtail_stock_images/__init__.py
wagtail_stock_images/engine.py
wagtail_stock_images/forms.py
wagtail_stock_images/settings.py
wagtail_stock_images/types.py
wagtail_stock_images/utils.py
wagtail_stock_images/views.py
wagtail_stock_images/wagtail_hooks.py
wagtail_stock_images/contrib/__init__.py
wagtail_stock_images/contrib/unsplash.py
wagtail_stock_images/locales/.gitkeep
wagtail_stock_images/migrations/__init__.py
wagtail_stock_images/templates/wagtail_stock_images/results.html
wagtail_stock_images/templates/wagtail_stock_images/save.html
wagtail_stock_images/templates/wagtail_stock_images/search.html
wagtail_stock_images-0.1.0.dist-info/LICENSE
wagtail_stock_images-0.1.0.dist-info/METADATA
wagtail_stock_images-0.1.0.dist-info/WHEEL
wagtail_stock_images-0.1.0.dist-info/top_level.txt
wagtail_stock_images-0.1.0.dist-info/RECORD
